./.gitignore
./.python-version
./PKG-INFO
./README.md
./__init__.py
./client.py
./pyproject.toml
ttt_client-0.1.2.dist-info/METADATA
ttt_client-0.1.2.dist-info/WHEEL
ttt_client-0.1.2.dist-info/entry_points.txt
ttt_client-0.1.2.dist-info/RECORD
