Metadata-Version: 2.4
Name: ttt-client
Version: 0.1.2
Summary: Terminal-based Tic-Tac-Toe game
Requires-Python: >=3.11
Requires-Dist: requests>=2.32.5
Requires-Dist: rich>=14.2.0
Requires-Dist: ttt-common>=0.1.0
Requires-Dist: websockets>=15.0.1
